<annotation>
	<folder>asian_female</folder>
	<filename>as_317.jpg</filename>
	<path>D:\races+gender\asian_female\as_317.jpg</path>
	<source>
		<database>Unknown</database>
	</source>
	<size>
		<width>265</width>
		<height>190</height>
		<depth>3</depth>
	</size>
	<segmented>0</segmented>
	<object>
		<name>asian_female</name>
		<pose>Unspecified</pose>
		<truncated>0</truncated>
		<difficult>0</difficult>
		<bndbox>
			<xmin>33</xmin>
			<ymin>6</ymin>
			<xmax>134</xmax>
			<ymax>105</ymax>
		</bndbox>
	</object>
</annotation>
