<annotation>
	<folder>New folder</folder>
	<filename>as_M_031.jpg</filename>
	<path>I:\New folder\as_M_031.jpg</path>
	<source>
		<database>Unknown</database>
	</source>
	<size>
		<width>183</width>
		<height>275</height>
		<depth>1</depth>
	</size>
	<segmented>0</segmented>
	<object>
		<name>asian_male</name>
		<pose>Unspecified</pose>
		<truncated>0</truncated>
		<difficult>0</difficult>
		<bndbox>
			<xmin>28</xmin>
			<ymin>18</ymin>
			<xmax>143</xmax>
			<ymax>203</ymax>
		</bndbox>
	</object>
</annotation>
