<annotation>
	<folder>black_male</folder>
	<filename>bm_{N000} (85).jpg</filename>
	<path>C:\Users\User\Desktop\black_male\bm_{N000} (85).jpg</path>
	<source>
		<database>Unknown</database>
	</source>
	<size>
		<width>241</width>
		<height>209</height>
		<depth>3</depth>
	</size>
	<segmented>0</segmented>
	<object>
		<name>black_male</name>
		<pose>Unspecified</pose>
		<truncated>1</truncated>
		<difficult>0</difficult>
		<bndbox>
			<xmin>81</xmin>
			<ymin>63</ymin>
			<xmax>177</xmax>
			<ymax>209</ymax>
		</bndbox>
	</object>
</annotation>
